{
    "services": [
      {
        "id": 1,
        "name": "Консультация юриста",
        "description": "Индивидуальная консультация по любым юридическим вопросам.",
        "price": 5000,
        "category": "Консультации",
        "duration": "1 час"
      },
      {
        "id": 2,
        "name": "Подготовка документов",
        "description": "Подготовка юридических документов для физических и юридических лиц.",
        "price": 10000,
        "category": "Документы",
        "duration": "3 часа"
      },
      {
        "id": 3,
        "name": "Составление договора",
        "description": "Составление и проверка договоров для физических и юридических лиц.",
        "price": 8000,
        "category": "Договоры",
        "duration": "2 часа"
      },
      {
        "id": 4,
        "name": "Судебное представительство",
        "description": "Защита интересов клиента в суде по гражданским делам.",
        "price": 25000,
        "category": "Судебные услуги",
        "duration": "По делу"
      },
      {
        "id": 5,
        "name": "Регистрация бизнеса",
        "description": "Помощь в регистрации юридического лица или ИП.",
        "price": 15000,
        "category": "Бизнес-услуги",
        "duration": "5 часов"
      },
      {
        "id": 6,
        "name": "Юридическое сопровождение бизнеса",
        "description": "Полное юридическое сопровождение бизнеса на всех этапах.",
        "price": 50000,
        "category": "Бизнес-услуги",
        "duration": "На месяц"
      },
      {
        "id": 7,
        "name": "Налоговая консультация",
        "description": "Консультация по вопросам налогового законодательства и оптимизации налогов.",
        "price": 7000,
        "category": "Налоги",
        "duration": "1.5 часа"
      },
      {
        "id": 8,
        "name": "Правовая экспертиза",
        "description": "Проверка правомерности действий и составление юридического заключения.",
        "price": 12000,
        "category": "Экспертиза",
        "duration": "2 часа"
      },
      {
        "id": 9,
        "name": "Юридическая помощь при ДТП",
        "description": "Консультации и помощь в решении вопросов по ДТП.",
        "price": 6000,
        "category": "Авто",
        "duration": "1 час"
      },
      {
        "id": 10,
        "name": "Оспаривание штрафов",
        "description": "Юридическая помощь при оспаривании штрафов и санкций.",
        "price": 4000,
        "category": "Авто",
        "duration": "1 час"
      }
    ]
  }
  